README.txt
setup.py
Playtools.egg-info/PKG-INFO
Playtools.egg-info/SOURCES.txt
Playtools.egg-info/dependency_links.txt
Playtools.egg-info/requires.txt
Playtools.egg-info/top_level.txt
bin/ptconvert
bin/ptstore
playtools/__init__.py
playtools/charsheet.py
playtools/common.py
playtools/convert.py
playtools/interfaces.py
playtools/rdfify.py
playtools/sparqly.py
playtools/util.py
playtools/hg/__init__.py
playtools/hg/hooks.py
playtools/plugins/__init__.py
playtools/plugins/charsheet.py
playtools/plugins/feats.py
playtools/plugins/monsters.py
playtools/plugins/skills.py
playtools/plugins/util.py
playtools/test/__init__.py
playtools/test/pttestutil.py
playtools/test/test_convert.py
playtools/test/test_pttestutil.py
playtools/test/test_sparqly.py
playtools/test/test_util.py