Metadata-Version: 1.0
Name: Playtools
Version: 0.1
Summary: Playtools for RPG Software
Home-page: http://goonmill.org/playtools/
Author: Cory Dodt
Author-email: pypi@spam.goonmill.org
License: UNKNOWN
Download-URL: http://playtools-source.goonmill.org/archive/tip.tar.gz
Platform: UNKNOWN
Classifier: Development Status :: 2 - Pre-Alpha
Classifier: Environment :: Console
Classifier: Environment :: Web Environment
Classifier: Intended Audience :: Developers
Classifier: License :: OSI Approved :: MIT License
Classifier: Operating System :: POSIX
Classifier: Programming Language :: Python
Classifier: Topic :: Games/Entertainment :: Role-Playing
Classifier: Topic :: Software Development :: Libraries
